[{"value":"78991","title":"Number of Rooms, 2011 (QS407EW)","description":"","variableId":"9865"},{"value":"217587","title":"Number of Rooms, 2011 (QS407EW)","description":"","variableId":"9866"},{"value":"589608","title":"Number of Rooms, 2011 (QS407EW)","description":"","variableId":"9867"},{"value":"791120","title":"Number of Rooms, 2011 (QS407EW)","description":"","variableId":"9868"},{"value":"672302","title":"Number of Rooms, 2011 (QS407EW)","description":"","variableId":"9869"},{"value":"459044","title":"Number of Rooms, 2011 (QS407EW)","description":"","variableId":"9870"},{"value":"218491","title":"Number of Rooms, 2011 (QS407EW)","description":"","variableId":"9871"},{"value":"125273","title":"Number of Rooms, 2011 (QS407EW)","description":"","variableId":"9872"},{"value":"113757","title":"Number of Rooms, 2011 (QS407EW)","description":"","variableId":"9873"},{"value":"3266173","title":"Number of Rooms, 2011 (QS407EW)","description":"","variableId":"9874"},{"value":"26","title":"Country of Birth (detailed), 2011 (QS203EW)","description":"","variableId":"10210"},{"value":"8173941","title":"Country of Birth (detailed), 2011 (QS203EW)","description":"","variableId":"10211"},{"value":"6174371","title":"Country of Birth (detailed), 2011 (QS203EW)","description":"","variableId":"10212"},{"value":"5175677","title":"Country of Birth (detailed), 2011 (QS203EW)","description":"","variableId":"10213"},{"value":"4997072","title":"Country of Birth (detailed), 2011 (QS203EW)","description":"","variableId":"10214"},{"value":"89527","title":"Country of Birth (detailed), 2011 (QS203EW)","description":"","variableId":"10215"},{"value":"32774","title":"Country of Birth (detailed), 2011 (QS203EW)","description":"","variableId":"10216"},{"value":"53828","title":"Country of Birth (detailed), 2011 (QS203EW)","description":"","variableId":"10217"},{"value":"544","title":"Country of Birth (detailed), 2011 (QS203EW)","description":"","variableId":"10218"},{"value":"1932","title":"Country of Birth (detailed), 2011 (QS203EW)","description":"","variableId":"10219"},{"value":"799","title":"Country of Birth (detailed), 2011 (QS203EW)","description":"","variableId":"10220"},{"value":"1445","title":"Country of Birth (detailed), 2011 (QS203EW)","description":"","variableId":"10221"},{"value":"202","title":"Country of Birth (detailed), 2011 (QS203EW)","description":"","variableId":"10222"},{"value":"760","title":"Country of Birth (detailed), 2011 (QS203EW)","description":"","variableId":"10223"},{"value":"129807","title":"Country of Birth (detailed), 2011 (QS203EW)","description":"","variableId":"10224"},{"value":"865681","title":"Country of Birth (detailed), 2011 (QS203EW)","description":"","variableId":"10225"},{"value":"711133","title":"Country of Birth (detailed), 2011 (QS203EW)","description":"","variableId":"10226"},{"value":"341981","title":"Country of Birth (detailed), 2011 (QS203EW)","description":"","variableId":"10227"},{"value":"66654","title":"Country of Birth (detailed), 2011 (QS203EW)","description":"","variableId":"10228"},{"value":"55476","title":"Country of Birth (detailed), 2011 (QS203EW)","description":"","variableId":"10229"},{"value":"62050","title":"Country of Birth (detailed), 2011 (QS203EW)","description":"","variableId":"10230"},{"value":"41041","title":"Country of Birth (detailed), 2011 (QS203EW)","description":"","variableId":"10231"},{"value":"35880","title":"Country of Birth (detailed), 2011 (QS203EW)","description":"","variableId":"10232"},{"value":"369152","title":"Country of Birth (detailed), 2011 (QS203EW)","description":"","variableId":"10233"},{"value":"39817","title":"Country of Birth (detailed), 2011 (QS203EW)","description":"","variableId":"10234"},{"value":"158300","title":"Country of Birth (detailed), 2011 (QS203EW)","description":"","variableId":"10235"},{"value":"44848","title":"Country of Birth (detailed), 2011 (QS203EW)","description":"","variableId":"10236"},{"value":"621613","title":"Country of Birth (detailed), 2011 (QS203EW)","description":"","variableId":"10237"},{"value":"52798","title":"Country of Birth (detailed), 2011 (QS203EW)","description":"","variableId":"10238"},{"value":"240354","title":"Country of Birth (detailed), 2011 (QS203EW)","description":"","variableId":"10239"},{"value":"62896","title":"Country of Birth (detailed), 2011 (QS203EW)","description":"","variableId":"10240"},{"value":"114718","title":"Country of Birth (detailed), 2011 (QS203EW)","description":"","variableId":"10241"},{"value":"322322","title":"Country of Birth (detailed), 2011 (QS203EW)","description":"","variableId":"10242"},{"value":"64212","title":"Country of Birth (detailed), 2011 (QS203EW)","description":"","variableId":"10243"},{"value":"65333","title":"Country of Birth (detailed), 2011 (QS203EW)","description":"","variableId":"10244"},{"value":"57765","title":"Country of Birth (detailed), 2011 (QS203EW)","description":"","variableId":"10245"},{"value":"21309","title":"Country of Birth (detailed), 2011 (QS203EW)","description":"","variableId":"10246"},{"value":"6139","title":"Country of Birth (detailed), 2011 (QS203EW)","description":"","variableId":"10247"},{"value":"966990","title":"Country of Birth (detailed), 2011 (QS203EW)","description":"","variableId":"10248"},{"value":"121794","title":"Country of Birth (detailed), 2011 (QS203EW)","description":"","variableId":"10249"},{"value":"37339","title":"Country of Birth (detailed), 2011 (QS203EW)","description":"","variableId":"10250"},{"value":"100934","title":"Country of Birth (detailed), 2011 (QS203EW)","description":"","variableId":"10251"},{"value":"39452","title":"Country of Birth (detailed), 2011 (QS203EW)","description":"","variableId":"10252"},{"value":"26435","title":"Country of Birth (detailed), 2011 (QS203EW)","description":"","variableId":"10253"},{"value":"626196","title":"Country of Birth (detailed), 2011 (QS203EW)","description":"","variableId":"10254"},{"value":"109948","title":"Country of Birth (detailed), 2011 (QS203EW)","description":"","variableId":"10255"},{"value":"262247","title":"Country of Birth (detailed), 2011 (QS203EW)","description":"","variableId":"10256"},{"value":"84542","title":"Country of Birth (detailed), 2011 (QS203EW)","description":"","variableId":"10257"},{"value":"113258","title":"Country of Birth (detailed), 2011 (QS203EW)","description":"","variableId":"10258"},{"value":"44199","title":"Country of Birth (detailed), 2011 (QS203EW)","description":"","variableId":"10259"},{"value":"4808","title":"Country of Birth (detailed), 2011 (QS203EW)","description":"","variableId":"10260"},{"value":"84661","title":"Country of Birth (detailed), 2011 (QS203EW)","description":"","variableId":"10261"},{"value":"25","title":"Country of Birth (detailed), 2011 (QS203EW)","description":"","variableId":"10262"},{"value":"80880","title":"Country of Birth (detailed), 2011 (QS203EW)","description":"","variableId":"10263"},{"value":"126187","title":"Country of Birth (detailed), 2011 (QS203EW)","description":"","variableId":"10264"},{"value":"154548","title":"Country of Birth (detailed), 2011 (QS203EW)","description":"","variableId":"10265"},{"value":"59596","title":"Country of Birth (detailed), 2011 (QS203EW)","description":"","variableId":"10266"},{"value":"94952","title":"Country of Birth (detailed), 2011 (QS203EW)","description":"","variableId":"10267"},{"value":"62740","title":"Country of Birth (detailed), 2011 (QS203EW)","description":"","variableId":"10268"},{"value":"113703","title":"Country of Birth (detailed), 2011 (QS203EW)","description":"","variableId":"10269"},{"value":"84455","title":"Country of Birth (detailed), 2011 (QS203EW)","description":"","variableId":"10270"},{"value":"35047","title":"Country of Birth (detailed), 2011 (QS203EW)","description":"","variableId":"10271"},{"value":"112457","title":"Country of Birth (detailed), 2011 (QS203EW)","description":"","variableId":"10272"},{"value":"57002","title":"Country of Birth (detailed), 2011 (QS203EW)","description":"","variableId":"10273"},{"value":"69059","title":"Country of Birth (detailed), 2011 (QS203EW)","description":"","variableId":"10274"},{"value":"326280","title":"Country of Birth (detailed), 2011 (QS203EW)","description":"","variableId":"10275"},{"value":"86134","title":"Country of Birth (detailed), 2011 (QS203EW)","description":"","variableId":"10276"},{"value":"63920","title":"Country of Birth (detailed), 2011 (QS203EW)","description":"","variableId":"10277"},{"value":"22214","title":"Country of Birth (detailed), 2011 (QS203EW)","description":"","variableId":"10278"},{"value":"5473","title":"Country of Birth (detailed), 2011 (QS203EW)","description":"","variableId":"10279"},{"value":"90315","title":"Country of Birth (detailed), 2011 (QS203EW)","description":"","variableId":"10280"},{"value":"144358","title":"Country of Birth (detailed), 2011 (QS203EW)","description":"","variableId":"10281"},{"value":"87467","title":"Country of Birth (detailed), 2011 (QS203EW)","description":"","variableId":"10282"},{"value":"56891","title":"Country of Birth (detailed), 2011 (QS203EW)","description":"","variableId":"10283"},{"value":"82528","title":"Country of Birth (detailed), 2011 (QS203EW)","description":"","variableId":"10284"},{"value":"53959","title":"Country of Birth (detailed), 2011 (QS203EW)","description":"","variableId":"10285"},{"value":"28569","title":"Country of Birth (detailed), 2011 (QS203EW)","description":"","variableId":"10286"},{"value":"2108","title":"Country of Birth (detailed), 2011 (QS203EW)","description":"","variableId":"10287"},{"value":"3266173","title":"Accommodation Type - Households, 2011 (QS402EW)","description":"","variableId":"8634"},{"value":"3230665","title":"Accommodation Type - Households, 2011 (QS402EW)","description":"","variableId":"8635"},{"value":"1579008","title":"Accommodation Type - Households, 2011 (QS402EW)","description":"","variableId":"8636"},{"value":"205088","title":"Accommodation Type - Households, 2011 (QS402EW)","description":"","variableId":"8637"},{"value":"617324","title":"Accommodation Type - Households, 2011 (QS402EW)","description":"","variableId":"8638"},{"value":"756596","title":"Accommodation Type - Households, 2011 (QS402EW)","description":"","variableId":"8639"},{"value":"1649118","title":"Accommodation Type - Households, 2011 (QS402EW)","description":"","variableId":"8640"},{"value":"1211075","title":"Accommodation Type - Households, 2011 (QS402EW)","description":"","variableId":"8641"},{"value":"382826","title":"Accommodation Type - Households, 2011 (QS402EW)","description":"","variableId":"8642"},{"value":"55217","title":"Accommodation Type - Households, 2011 (QS402EW)","description":"","variableId":"8643"},{"value":"2539","title":"Accommodation Type - Households, 2011 (QS402EW)","description":"","variableId":"8644"},{"value":"35508","title":"Accommodation Type - Households, 2011 (QS402EW)","description":"","variableId":"8645"},{"value":"8073700","title":"Accommodation Type - People, 2011 (QS401EW)","description":"","variableId":"9420"},{"value":"8009602","title":"Accommodation Type - People, 2011 (QS401EW)","description":"","variableId":"9421"},{"value":"4582208","title":"Accommodation Type - People, 2011 (QS401EW)","description":"","variableId":"9422"},{"value":"618858","title":"Accommodation Type - People, 2011 (QS401EW)","description":"","variableId":"9423"},{"value":"1831596","title":"Accommodation Type - People, 2011 (QS401EW)","description":"","variableId":"9424"},{"value":"2131754","title":"Accommodation Type - People, 2011 (QS401EW)","description":"","variableId":"9425"},{"value":"3421994","title":"Accommodation Type - People, 2011 (QS401EW)","description":"","variableId":"9426"},{"value":"2538578","title":"Accommodation Type - People, 2011 (QS401EW)","description":"","variableId":"9427"},{"value":"756351","title":"Accommodation Type - People, 2011 (QS401EW)","description":"","variableId":"9428"},{"value":"127065","title":"Accommodation Type - People, 2011 (QS401EW)","description":"","variableId":"9429"},{"value":"5400","title":"Accommodation Type - People, 2011 (QS401EW)","description":"","variableId":"9430"},{"value":"64098","title":"Accommodation Type - People, 2011 (QS401EW)","description":"","variableId":"9431"},{"value":"6450430","title":"Adult Lifestage (Alternative Adult Definition), 2011 (QS110EW)","description":"","variableId":"9628"},{"value":"966197","title":"Adult Lifestage (Alternative Adult Definition), 2011 (QS110EW)","description":"","variableId":"9629"},{"value":"499047","title":"Adult Lifestage (Alternative Adult Definition), 2011 (QS110EW)","description":"","variableId":"9630"},{"value":"467150","title":"Adult Lifestage (Alternative Adult Definition), 2011 (QS110EW)","description":"","variableId":"9631"},{"value":"1618147","title":"Adult Lifestage (Alternative Adult Definition), 2011 (QS110EW)","description":"","variableId":"9632"},{"value":"1109608","title":"Adult Lifestage (Alternative Adult Definition), 2011 (QS110EW)","description":"","variableId":"9633"},{"value":"381446","title":"Adult Lifestage (Alternative Adult Definition), 2011 (QS110EW)","description":"","variableId":"9634"},{"value":"85260","title":"Adult Lifestage (Alternative Adult Definition), 2011 (QS110EW)","description":"","variableId":"9635"},{"value":"27433","title":"Adult Lifestage (Alternative Adult Definition), 2011 (QS110EW)","description":"","variableId":"9636"},{"value":"14400","title":"Adult Lifestage (Alternative Adult Definition), 2011 (QS110EW)","description":"","variableId":"9637"},{"value":"2279369","title":"Adult Lifestage (Alternative Adult Definition), 2011 (QS110EW)","description":"","variableId":"9638"},{"value":"1097189","title":"Adult Lifestage (Alternative Adult Definition), 2011 (QS110EW)","description":"","variableId":"9639"},{"value":"433530","title":"Adult Lifestage (Alternative Adult Definition), 2011 (QS110EW)","description":"","variableId":"9640"},{"value":"360930","title":"Adult Lifestage (Alternative Adult Definition), 2011 (QS110EW)","description":"","variableId":"9641"},{"value":"272619","title":"Adult Lifestage (Alternative Adult Definition), 2011 (QS110EW)","description":"","variableId":"9642"},{"value":"115101","title":"Adult Lifestage (Alternative Adult Definition), 2011 (QS110EW)","description":"","variableId":"9643"},{"value":"710081","title":"Adult Lifestage (Alternative Adult Definition), 2011 (QS110EW)","description":"","variableId":"9644"},{"value":"156349","title":"Adult Lifestage (Alternative Adult Definition), 2011 (QS110EW)","description":"","variableId":"9645"},{"value":"457574","title":"Adult Lifestage (Alternative Adult Definition), 2011 (QS110EW)","description":"","variableId":"9646"},{"value":"96158","title":"Adult Lifestage (Alternative Adult Definition), 2011 (QS110EW)","description":"","variableId":"9647"},{"value":"468537","title":"Adult Lifestage (Alternative Adult Definition), 2011 (QS110EW)","description":"","variableId":"9648"},{"value":"134138","title":"Adult Lifestage (Alternative Adult Definition), 2011 (QS110EW)","description":"","variableId":"9649"},{"value":"301206","title":"Adult Lifestage (Alternative Adult Definition), 2011 (QS110EW)","description":"","variableId":"9650"},{"value":"33193","title":"Adult Lifestage (Alternative Adult Definition), 2011 (QS110EW)","description":"","variableId":"9651"},{"value":"408099","title":"Adult Lifestage (Alternative Adult Definition), 2011 (QS110EW)","description":"","variableId":"9652"},{"value":"177884","title":"Adult Lifestage (Alternative Adult Definition), 2011 (QS110EW)","description":"","variableId":"9653"},{"value":"230215","title":"Adult Lifestage (Alternative Adult Definition), 2011 (QS110EW)","description":"","variableId":"9654"},{"value":"8173941","title":"Age by Single Year, 2011 (QS103EW)","description":"","variableId":"9447"},{"value":"124785","title":"Age by Single Year, 2011 (QS103EW)","description":"","variableId":"9448"},{"value":"121638","title":"Age by Single Year, 2011 (QS103EW)","description":"","variableId":"9449"},{"value":"117576","title":"Age by Single Year, 2011 (QS103EW)","description":"","variableId":"9450"},{"value":"116154","title":"Age by Single Year, 2011 (QS103EW)","description":"","variableId":"9451"},{"value":"111342","title":"Age by Single Year, 2011 (QS103EW)","description":"","variableId":"9452"},{"value":"105945","title":"Age by Single Year, 2011 (QS103EW)","description":"","variableId":"9453"},{"value":"99271","title":"Age by Single Year, 2011 (QS103EW)","description":"","variableId":"9454"},{"value":"95879","title":"Age by Single Year, 2011 (QS103EW)","description":"","variableId":"9455"},{"value":"91736","title":"Age by Single Year, 2011 (QS103EW)","description":"","variableId":"9456"},{"value":"89978","title":"Age by Single Year, 2011 (QS103EW)","description":"","variableId":"9457"},{"value":"91000","title":"Age by Single Year, 2011 (QS103EW)","description":"","variableId":"9458"},{"value":"91387","title":"Age by Single Year, 2011 (QS103EW)","description":"","variableId":"9459"},{"value":"90730","title":"Age by Single Year, 2011 (QS103EW)","description":"","variableId":"9460"},{"value":"91820","title":"Age by Single Year, 2011 (QS103EW)","description":"","variableId":"9461"},{"value":"91928","title":"Age by Single Year, 2011 (QS103EW)","description":"","variableId":"9462"},{"value":"93599","title":"Age by Single Year, 2011 (QS103EW)","description":"","variableId":"9463"},{"value":"92326","title":"Age by Single Year, 2011 (QS103EW)","description":"","variableId":"9464"},{"value":"94300","title":"Age by Single Year, 2011 (QS103EW)","description":"","variableId":"9465"},{"value":"94749","title":"Age by Single Year, 2011 (QS103EW)","description":"","variableId":"9466"},{"value":"96685","title":"Age by Single Year, 2011 (QS103EW)","description":"","variableId":"9467"},{"value":"105532","title":"Age by Single Year, 2011 (QS103EW)","description":"","variableId":"9468"},{"value":"111717","title":"Age by Single Year, 2011 (QS103EW)","description":"","variableId":"9469"},{"value":"125743","title":"Age by Single Year, 2011 (QS103EW)","description":"","variableId":"9470"},{"value":"140067","title":"Age by Single Year, 2011 (QS103EW)","description":"","variableId":"9471"},{"value":"146913","title":"Age by Single Year, 2011 (QS103EW)","description":"","variableId":"9472"},{"value":"159512","title":"Age by Single Year, 2011 (QS103EW)","description":"","variableId":"9473"},{"value":"164580","title":"Age by Single Year, 2011 (QS103EW)","description":"","variableId":"9474"},{"value":"166626","title":"Age by Single Year, 2011 (QS103EW)","description":"","variableId":"9475"},{"value":"170699","title":"Age by Single Year, 2011 (QS103EW)","description":"","variableId":"9476"},{"value":"171549","title":"Age by Single Year, 2011 (QS103EW)","description":"","variableId":"9477"},{"value":"172672","title":"Age by Single Year, 2011 (QS103EW)","description":"","variableId":"9478"},{"value":"168002","title":"Age by Single Year, 2011 (QS103EW)","description":"","variableId":"9479"},{"value":"160603","title":"Age by Single Year, 2011 (QS103EW)","description":"","variableId":"9480"},{"value":"149733","title":"Age by Single Year, 2011 (QS103EW)","description":"","variableId":"9481"},{"value":"145878","title":"Age by Single Year, 2011 (QS103EW)","description":"","variableId":"9482"},{"value":"138539","title":"Age by Single Year, 2011 (QS103EW)","description":"","variableId":"9483"},{"value":"135847","title":"Age by Single Year, 2011 (QS103EW)","description":"","variableId":"9484"},{"value":"131289","title":"Age by Single Year, 2011 (QS103EW)","description":"","variableId":"9485"},{"value":"130484","title":"Age by Single Year, 2011 (QS103EW)","description":"","variableId":"9486"},{"value":"127887","title":"Age by Single Year, 2011 (QS103EW)","description":"","variableId":"9487"},{"value":"126348","title":"Age by Single Year, 2011 (QS103EW)","description":"","variableId":"9488"},{"value":"122375","title":"Age by Single Year, 2011 (QS103EW)","description":"","variableId":"9489"},{"value":"121869","title":"Age by Single Year, 2011 (QS103EW)","description":"","variableId":"9490"},{"value":"120115","title":"Age by Single Year, 2011 (QS103EW)","description":"","variableId":"9491"},{"value":"119313","title":"Age by Single Year, 2011 (QS103EW)","description":"","variableId":"9492"},{"value":"117360","title":"Age by Single Year, 2011 (QS103EW)","description":"","variableId":"9493"},{"value":"115630","title":"Age by Single Year, 2011 (QS103EW)","description":"","variableId":"9494"},{"value":"112374","title":"Age by Single Year, 2011 (QS103EW)","description":"","variableId":"9495"},{"value":"108619","title":"Age by Single Year, 2011 (QS103EW)","description":"","variableId":"9496"},{"value":"102673","title":"Age by Single Year, 2011 (QS103EW)","description":"","variableId":"9497"},{"value":"101510","title":"Age by Single Year, 2011 (QS103EW)","description":"","variableId":"9498"},{"value":"95508","title":"Age by Single Year, 2011 (QS103EW)","description":"","variableId":"9499"},{"value":"92326","title":"Age by Single Year, 2011 (QS103EW)","description":"","variableId":"9500"},{"value":"87938","title":"Age by Single Year, 2011 (QS103EW)","description":"","variableId":"9501"},{"value":"84008","title":"Age by Single Year, 2011 (QS103EW)","description":"","variableId":"9502"},{"value":"80756","title":"Age by Single Year, 2011 (QS103EW)","description":"","variableId":"9503"},{"value":"76880","title":"Age by Single Year, 2011 (QS103EW)","description":"","variableId":"9504"},{"value":"73771","title":"Age by Single Year, 2011 (QS103EW)","description":"","variableId":"9505"},{"value":"71558","title":"Age by Single Year, 2011 (QS103EW)","description":"","variableId":"9506"},{"value":"68971","title":"Age by Single Year, 2011 (QS103EW)","description":"","variableId":"9507"},{"value":"67874","title":"Age by Single Year, 2011 (QS103EW)","description":"","variableId":"9508"},{"value":"67658","title":"Age by Single Year, 2011 (QS103EW)","description":"","variableId":"9509"},{"value":"67247","title":"Age by Single Year, 2011 (QS103EW)","description":"","variableId":"9510"},{"value":"70128","title":"Age by Single Year, 2011 (QS103EW)","description":"","variableId":"9511"},{"value":"69683","title":"Age by Single Year, 2011 (QS103EW)","description":"","variableId":"9512"},{"value":"55510","title":"Age by Single Year, 2011 (QS103EW)","description":"","variableId":"9513"},{"value":"55525","title":"Age by Single Year, 2011 (QS103EW)","description":"","variableId":"9514"},{"value":"51880","title":"Age by Single Year, 2011 (QS103EW)","description":"","variableId":"9515"},{"value":"50118","title":"Age by Single Year, 2011 (QS103EW)","description":"","variableId":"9516"},{"value":"43739","title":"Age by Single Year, 2011 (QS103EW)","description":"","variableId":"9517"},{"value":"43199","title":"Age by Single Year, 2011 (QS103EW)","description":"","variableId":"9518"},{"value":"45428","title":"Age by Single Year, 2011 (QS103EW)","description":"","variableId":"9519"},{"value":"44325","title":"Age by Single Year, 2011 (QS103EW)","description":"","variableId":"9520"},{"value":"42211","title":"Age by Single Year, 2011 (QS103EW)","description":"","variableId":"9521"},{"value":"41123","title":"Age by Single Year, 2011 (QS103EW)","description":"","variableId":"9522"},{"value":"39084","title":"Age by Single Year, 2011 (QS103EW)","description":"","variableId":"9523"},{"value":"37248","title":"Age by Single Year, 2011 (QS103EW)","description":"","variableId":"9524"},{"value":"34519","title":"Age by Single Year, 2011 (QS103EW)","description":"","variableId":"9525"},{"value":"33740","title":"Age by Single Year, 2011 (QS103EW)","description":"","variableId":"9526"},{"value":"32240","title":"Age by Single Year, 2011 (QS103EW)","description":"","variableId":"9527"},{"value":"31410","title":"Age by Single Year, 2011 (QS103EW)","description":"","variableId":"9528"},{"value":"29118","title":"Age by Single Year, 2011 (QS103EW)","description":"","variableId":"9529"},{"value":"25944","title":"Age by Single Year, 2011 (QS103EW)","description":"","variableId":"9530"},{"value":"23692","title":"Age by Single Year, 2011 (QS103EW)","description":"","variableId":"9531"},{"value":"21666","title":"Age by Single Year, 2011 (QS103EW)","description":"","variableId":"9532"},{"value":"19830","title":"Age by Single Year, 2011 (QS103EW)","description":"","variableId":"9533"},{"value":"18067","title":"Age by Single Year, 2011 (QS103EW)","description":"","variableId":"9534"},{"value":"16007","title":"Age by Single Year, 2011 (QS103EW)","description":"","variableId":"9535"},{"value":"14255","title":"Age by Single Year, 2011 (QS103EW)","description":"","variableId":"9536"},{"value":"12415","title":"Age by Single Year, 2011 (QS103EW)","description":"","variableId":"9537"},{"value":"11190","title":"Age by Single Year, 2011 (QS103EW)","description":"","variableId":"9538"},{"value":"8730","title":"Age by Single Year, 2011 (QS103EW)","description":"","variableId":"9539"},{"value":"4926","title":"Age by Single Year, 2011 (QS103EW)","description":"","variableId":"9540"},{"value":"4061","title":"Age by Single Year, 2011 (QS103EW)","description":"","variableId":"9541"},{"value":"352612","title":"Method of Travel to Work, 2011 (QS701EW)","description":"","variableId":"9763"},{"value":"78991","title":"Number of Rooms, 2011 (QS407EW)","description":"","variableId":"9865"},{"value":"3572","title":"Age by Single Year, 2011 (QS103EW)","description":"","variableId":"9542"},{"value":"2866","title":"Age by Single Year, 2011 (QS103EW)","description":"","variableId":"9543"},{"value":"2224","title":"Age by Single Year, 2011 (QS103EW)","description":"","variableId":"9544"},{"value":"1667","title":"Age by Single Year, 2011 (QS103EW)","description":"","variableId":"9545"},{"value":"1166","title":"Age by Single Year, 2011 (QS103EW)","description":"","variableId":"9546"},{"value":"778","title":"Age by Single Year, 2011 (QS103EW)","description":"","variableId":"9547"},{"value":"1276","title":"Age by Single Year, 2011 (QS103EW)","description":"","variableId":"9548"},{"value":"8173941","title":"Age of Arrival in the UK, 2011 (QS802EW)","description":"","variableId":"9301"},{"value":"5175677","title":"Age of Arrival in the UK, 2011 (QS802EW)","description":"","variableId":"9302"},{"value":"262052","title":"Age of Arrival in the UK, 2011 (QS802EW)","description":"","variableId":"9303"},{"value":"118250","title":"Age of Arrival in the UK, 2011 (QS802EW)","description":"","variableId":"9304"},{"value":"77881","title":"Age of Arrival in the UK, 2011 (QS802EW)","description":"","variableId":"9305"},{"value":"200785","title":"Age of Arrival in the UK, 2011 (QS802EW)","description":"","variableId":"9306"},{"value":"50012","title":"Age of Arrival in the UK, 2011 (QS802EW)","description":"","variableId":"9307"},{"value":"134765","title":"Age of Arrival in the UK, 2011 (QS802EW)","description":"","variableId":"9308"},{"value":"205550","title":"Age of Arrival in the UK, 2011 (QS802EW)","description":"","variableId":"9309"},{"value":"661275","title":"Age of Arrival in the UK, 2011 (QS802EW)","description":"","variableId":"9310"},{"value":"578875","title":"Age of Arrival in the UK, 2011 (QS802EW)","description":"","variableId":"9311"},{"value":"567026","title":"Age of Arrival in the UK, 2011 (QS802EW)","description":"","variableId":"9312"},{"value":"108192","title":"Age of Arrival in the UK, 2011 (QS802EW)","description":"","variableId":"9313"},{"value":"14084","title":"Age of Arrival in the UK, 2011 (QS802EW)","description":"","variableId":"9314"},{"value":"14952","title":"Age of Arrival in the UK, 2011 (QS802EW)","description":"","variableId":"9315"},{"value":"3853","title":"Age of Arrival in the UK, 2011 (QS802EW)","description":"","variableId":"9316"},{"value":"511","title":"Age of Arrival in the UK, 2011 (QS802EW)","description":"","variableId":"9317"},{"value":"201","title":"Age of Arrival in the UK, 2011 (QS802EW)","description":"","variableId":"9318"},{"value":"6253","title":"Armed Forces, 2011 (QS121EW)","description":"","variableId":"9271"},{"value":"4936","title":"Armed Forces, 2011 (QS121EW)","description":"","variableId":"9272"},{"value":"1317","title":"Armed Forces, 2011 (QS121EW)","description":"","variableId":"9273"},{"value":"3266173","title":"Car or Van Availability, 2011 (QS416EW)","description":"","variableId":"10414"},{"value":"1357251","title":"Car or Van Availability, 2011 (QS416EW)","description":"","variableId":"10415"},{"value":"1324032","title":"Car or Van Availability, 2011 (QS416EW)","description":"","variableId":"10416"},{"value":"458659","title":"Car or Van Availability, 2011 (QS416EW)","description":"","variableId":"10417"},{"value":"95619","title":"Car or Van Availability, 2011 (QS416EW)","description":"","variableId":"10418"},{"value":"30612","title":"Car or Van Availability, 2011 (QS416EW)","description":"","variableId":"10419"},{"value":"2664414","title":"Car or Van Availability, 2011 (QS416EW)","description":"","variableId":"10420"},{"value":"92411","title":"Central Heating, 2011 (QS415EW)","description":"","variableId":"9910"},{"value":"2571307","title":"Central Heating, 2011 (QS415EW)","description":"","variableId":"9911"},{"value":"325147","title":"Central Heating, 2011 (QS415EW)","description":"","variableId":"9912"},{"value":"12115","title":"Central Heating, 2011 (QS415EW)","description":"","variableId":"9913"},{"value":"1598","title":"Central Heating, 2011 (QS415EW)","description":"","variableId":"9914"},{"value":"120347","title":"Central Heating, 2011 (QS415EW)","description":"","variableId":"9915"},{"value":"143248","title":"Central Heating, 2011 (QS415EW)","description":"","variableId":"9916"},{"value":"3266173","title":"Central Heating, 2011 (QS415EW)","description":"","variableId":"9917"},{"value":"6382","title":"Communal Establishment Management and Type - Communal Establishment, 2011 (QS420EW)","description":"","variableId":"9677"},{"value":"2534","title":"Communal Establishment Management and Type - Communal Establishment, 2011 (QS420EW)","description":"","variableId":"9678"},{"value":"155","title":"Communal Establishment Management and Type - Communal Establishment, 2011 (QS420EW)","description":"","variableId":"9679"},{"value":"24","title":"Communal Establishment Management and Type - Communal Establishment, 2011 (QS420EW)","description":"","variableId":"9680"},{"value":"73","title":"Communal Establishment Management and Type - Communal Establishment, 2011 (QS420EW)","description":"","variableId":"9681"},{"value":"58","title":"Communal Establishment Management and Type - Communal Establishment, 2011 (QS420EW)","description":"","variableId":"9682"},{"value":"166","title":"Communal Establishment Management and Type - Communal Establishment, 2011 (QS420EW)","description":"","variableId":"9683"},{"value":"11","title":"Communal Establishment Management and Type - Communal Establishment, 2011 (QS420EW)","description":"","variableId":"9684"},{"value":"7","title":"Communal Establishment Management and Type - Communal Establishment, 2011 (QS420EW)","description":"","variableId":"9685"},{"value":"95","title":"Communal Establishment Management and Type - Communal Establishment, 2011 (QS420EW)","description":"","variableId":"9686"},{"value":"53","title":"Communal Establishment Management and Type - Communal Establishment, 2011 (QS420EW)","description":"","variableId":"9687"},{"value":"123","title":"Communal Establishment Management and Type - Communal Establishment, 2011 (QS420EW)","description":"","variableId":"9688"},{"value":"75","title":"Communal Establishment Management and Type - Communal Establishment, 2011 (QS420EW)","description":"","variableId":"9689"},{"value":"48","title":"Communal Establishment Management and Type - Communal Establishment, 2011 (QS420EW)","description":"","variableId":"9690"},{"value":"2090","title":"Communal Establishment Management and Type - Communal Establishment, 2011 (QS420EW)","description":"","variableId":"9691"},{"value":"341","title":"Communal Establishment Management and Type - Communal Establishment, 2011 (QS420EW)","description":"","variableId":"9692"},{"value":"1434","title":"Communal Establishment Management and Type - Communal Establishment, 2011 (QS420EW)","description":"","variableId":"9693"},{"value":"34","title":"Communal Establishment Management and Type - Communal Establishment, 2011 (QS420EW)","description":"","variableId":"9694"},{"value":"44","title":"Communal Establishment Management and Type - Communal Establishment, 2011 (QS420EW)","description":"","variableId":"9695"},{"value":"61","title":"Communal Establishment Management and Type - Communal Establishment, 2011 (QS420EW)","description":"","variableId":"9696"},{"value":"176","title":"Communal Establishment Management and Type - Communal Establishment, 2011 (QS420EW)","description":"","variableId":"9697"},{"value":"2193","title":"Communal Establishment Management and Type - Communal Establishment, 2011 (QS420EW)","description":"","variableId":"9698"},{"value":"21","title":"Communal Establishment Management and Type - Communal Establishment, 2011 (QS420EW)","description":"","variableId":"9699"},{"value":"8","title":"Communal Establishment Management and Type - Communal Establishment, 2011 (QS420EW)","description":"","variableId":"9700"},{"value":"10","title":"Communal Establishment Management and Type - Communal Establishment, 2011 (QS420EW)","description":"","variableId":"9701"},{"value":"11","title":"Communal Establishment Management and Type - Communal Establishment, 2011 (QS420EW)","description":"","variableId":"9702"},{"value":"406","title":"Communal Establishment Management and Type - Communal Establishment, 2011 (QS420EW)","description":"","variableId":"9703"},{"value":"1003","title":"Communal Establishment Management and Type - Communal Establishment, 2011 (QS420EW)","description":"","variableId":"9704"},{"value":"362","title":"Communal Establishment Management and Type - Communal Establishment, 2011 (QS420EW)","description":"","variableId":"9705"},{"value":"6","title":"Communal Establishment Management and Type - Communal Establishment, 2011 (QS420EW)","description":"","variableId":"9706"},{"value":"72","title":"Communal Establishment Management and Type - Communal Establishment, 2011 (QS420EW)","description":"","variableId":"9707"},{"value":"116","title":"Communal Establishment Management and Type - Communal Establishment, 2011 (QS420EW)","description":"","variableId":"9708"},{"value":"50","title":"Communal Establishment Management and Type - Communal Establishment, 2011 (QS420EW)","description":"","variableId":"9709"},{"value":"128","title":"Communal Establishment Management and Type - Communal Establishment, 2011 (QS420EW)","description":"","variableId":"9710"},{"value":"1655","title":"Communal Establishment Management and Type - Communal Establishment, 2011 (QS420EW)","description":"","variableId":"9711"},{"value":"100241","title":"Communal Establishment Management and Type - People, 2011 (QS421EW)","description":"","variableId":"9712"},{"value":"39716","title":"Communal Establishment Management and Type - People, 2011 (QS421EW)","description":"","variableId":"9713"},{"value":"2249","title":"Communal Establishment Management and Type - People, 2011 (QS421EW)","description":"","variableId":"9714"},{"value":"270","title":"Communal Establishment Management and Type - People, 2011 (QS421EW)","description":"","variableId":"9715"},{"value":"1581","title":"Communal Establishment Management and Type - People, 2011 (QS421EW)","description":"","variableId":"9716"},{"value":"398","title":"Communal Establishment Management and Type - People, 2011 (QS421EW)","description":"","variableId":"9717"},{"value":"1813","title":"Communal Establishment Management and Type - People, 2011 (QS421EW)","description":"","variableId":"9718"},{"value":"40","title":"Communal Establishment Management and Type - People, 2011 (QS421EW)","description":"","variableId":"9719"},{"value":"212","title":"Communal Establishment Management and Type - People, 2011 (QS421EW)","description":"","variableId":"9720"},{"value":"1248","title":"Communal Establishment Management and Type - People, 2011 (QS421EW)","description":"","variableId":"9721"},{"value":"313","title":"Communal Establishment Management and Type - People, 2011 (QS421EW)","description":"","variableId":"9722"},{"value":"1514","title":"Communal Establishment Management and Type - People, 2011 (QS421EW)","description":"","variableId":"9723"},{"value":"1064","title":"Communal Establishment Management and Type - People, 2011 (QS421EW)","description":"","variableId":"9724"},{"value":"450","title":"Communal Establishment Management and Type - People, 2011 (QS421EW)","description":"","variableId":"9725"},{"value":"34140","title":"Communal Establishment Management and Type - People, 2011 (QS421EW)","description":"","variableId":"9726"},{"value":"14054","title":"Communal Establishment Management and Type - People, 2011 (QS421EW)","description":"","variableId":"9727"},{"value":"17587","title":"Communal Establishment Management and Type - People, 2011 (QS421EW)","description":"","variableId":"9728"},{"value":"125","title":"Communal Establishment Management and Type - People, 2011 (QS421EW)","description":"","variableId":"9729"},{"value":"565","title":"Communal Establishment Management and Type - People, 2011 (QS421EW)","description":"","variableId":"9730"},{"value":"588","title":"Communal Establishment Management and Type - People, 2011 (QS421EW)","description":"","variableId":"9731"},{"value":"1221","title":"Communal Establishment Management and Type - People, 2011 (QS421EW)","description":"","variableId":"9732"},{"value":"57758","title":"Communal Establishment Management and Type - People, 2011 (QS421EW)","description":"","variableId":"9733"},{"value":"1577","title":"Communal Establishment Management and Type - People, 2011 (QS421EW)","description":"","variableId":"9734"},{"value":"3855","title":"Communal Establishment Management and Type - People, 2011 (QS421EW)","description":"","variableId":"9735"},{"value":"174","title":"Communal Establishment Management and Type - People, 2011 (QS421EW)","description":"","variableId":"9736"},{"value":"301","title":"Communal Establishment Management and Type - People, 2011 (QS421EW)","description":"","variableId":"9737"},{"value":"40074","title":"Communal Establishment Management and Type - People, 2011 (QS421EW)","description":"","variableId":"9738"},{"value":"2290","title":"Communal Establishment Management and Type - People, 2011 (QS421EW)","description":"","variableId":"9739"},{"value":"6056","title":"Communal Establishment Management and Type - People, 2011 (QS421EW)","description":"","variableId":"9740"},{"value":"3","title":"Communal Establishment Management and Type - People, 2011 (QS421EW)","description":"","variableId":"9741"},{"value":"380","title":"Communal Establishment Management and Type - People, 2011 (QS421EW)","description":"","variableId":"9742"},{"value":"1056","title":"Communal Establishment Management and Type - People, 2011 (QS421EW)","description":"","variableId":"9743"},{"value":"755","title":"Communal Establishment Management and Type - People, 2011 (QS421EW)","description":"","variableId":"9744"},{"value":"1237","title":"Communal Establishment Management and Type - People, 2011 (QS421EW)","description":"","variableId":"9745"},{"value":"2767","title":"Communal Establishment Management and Type - People, 2011 (QS421EW)","description":"","variableId":"9746"},{"value":"3358163","title":"Dwellings, 2011 (QS418EW)","description":"","variableId":"9568"},{"value":"3349011","title":"Dwellings, 2011 (QS418EW)","description":"","variableId":"9569"},{"value":"9152","title":"Dwellings, 2011 (QS418EW)","description":"","variableId":"9570"},{"value":"181694","title":"Economic Activity - Full-Time Students, 2011 (QS603EW)","description":"","variableId":"9993"},{"value":"66820","title":"Economic Activity - Full-Time Students, 2011 (QS603EW)","description":"","variableId":"9994"},{"value":"451778","title":"Economic Activity - Full-Time Students, 2011 (QS603EW)","description":"","variableId":"9995"},{"value":"700292","title":"Economic Activity - Full-Time Students, 2011 (QS603EW)","description":"","variableId":"9996"},{"value":"558351","title":"Economic Activity of Household Reference Persons, 2011 (QS602EW)","description":"","variableId":"9796"},{"value":"72659","title":"Economic Activity of Household Reference Persons, 2011 (QS602EW)","description":"","variableId":"9797"},{"value":"3266173","title":"Economic Activity of Household Reference Persons, 2011 (QS602EW)","description":"","variableId":"9798"},{"value":"2369951","title":"Economic Activity of Household Reference Persons, 2011 (QS602EW)","description":"","variableId":"9799"},{"value":"279198","title":"Economic Activity of Household Reference Persons, 2011 (QS602EW)","description":"","variableId":"9800"},{"value":"1459676","title":"Economic Activity of Household Reference Persons, 2011 (QS602EW)","description":"","variableId":"9801"},{"value":"15773","title":"Economic Activity of Household Reference Persons, 2011 (QS602EW)","description":"","variableId":"9802"},{"value":"94302","title":"Economic Activity of Household Reference Persons, 2011 (QS602EW)","description":"","variableId":"9803"},{"value":"88782","title":"Economic Activity of Household Reference Persons, 2011 (QS602EW)","description":"","variableId":"9804"},{"value":"253374","title":"Economic Activity of Household Reference Persons, 2011 (QS602EW)","description":"","variableId":"9805"},{"value":"127519","title":"Economic Activity of Household Reference Persons, 2011 (QS602EW)","description":"","variableId":"9806"},{"value":"51327","title":"Economic Activity of Household Reference Persons, 2011 (QS602EW)","description":"","variableId":"9807"},{"value":"896222","title":"Economic Activity of Household Reference Persons, 2011 (QS602EW)","description":"","variableId":"9808"},{"value":"52242","title":"Economic Activity of Household Reference Persons, 2011 (QS602EW)","description":"","variableId":"9809"},{"value":"79375","title":"Economic Activity of Household Reference Persons, 2011 (QS602EW)","description":"","variableId":"9810"},{"value":"133595","title":"Economic Activity of Household Reference Persons, 2011 (QS602EW)","description":"","variableId":"9811"},{"value":"512057","title":"Economic Activity, 2011 (QS601EW)","description":"","variableId":"10011"},{"value":"195793","title":"Economic Activity, 2011 (QS601EW)","description":"","variableId":"10012"},{"value":"1733265","title":"Economic Activity, 2011 (QS601EW)","description":"","variableId":"10013"},{"value":"477543","title":"Economic Activity, 2011 (QS601EW)","description":"","variableId":"10014"},{"value":"320880","title":"Economic Activity, 2011 (QS601EW)","description":"","variableId":"10015"},{"value":"226992","title":"Economic Activity, 2011 (QS601EW)","description":"","variableId":"10016"},{"value":"4384217","title":"Economic Activity, 2011 (QS601EW)","description":"","variableId":"10017"},{"value":"666513","title":"Economic Activity, 2011 (QS601EW)","description":"","variableId":"10018"},{"value":"2437797","title":"Economic Activity, 2011 (QS601EW)","description":"","variableId":"10019"},{"value":"28553","title":"Economic Activity, 2011 (QS601EW)","description":"","variableId":"10020"},{"value":"123432","title":"Economic Activity, 2011 (QS601EW)","description":"","variableId":"10021"},{"value":"192724","title":"Economic Activity, 2011 (QS601EW)","description":"","variableId":"10022"},{"value":"368184","title":"Economic Activity, 2011 (QS601EW)","description":"","variableId":"10023"},{"value":"318500","title":"Economic Activity, 2011 (QS601EW)","description":"","variableId":"10024"},{"value":"248514","title":"Economic Activity, 2011 (QS601EW)","description":"","variableId":"10025"},{"value":"6117482","title":"Economic Activity, 2011 (QS601EW)","description":"","variableId":"10026"},{"value":"175974","title":"Ethnic Group, 2011 (QS201EW)","description":"","variableId":"10118"},{"value":"1033981","title":"Ethnic Group, 2011 (QS201EW)","description":"","variableId":"10119"},{"value":"8173941","title":"Ethnic Group, 2011 (QS201EW)","description":"","variableId":"10120"},{"value":"3669284","title":"Ethnic Group, 2011 (QS201EW)","description":"","variableId":"10121"},{"value":"8196","title":"Ethnic Group, 2011 (QS201EW)","description":"","variableId":"10122"},{"value":"119425","title":"Ethnic Group, 2011 (QS201EW)","description":"","variableId":"10123"},{"value":"65479","title":"Ethnic Group, 2011 (QS201EW)","description":"","variableId":"10124"},{"value":"101500","title":"Ethnic Group, 2011 (QS201EW)","description":"","variableId":"10125"},{"value":"118875","title":"Ethnic Group, 2011 (QS201EW)","description":"","variableId":"10126"},{"value":"542857","title":"Ethnic Group, 2011 (QS201EW)","description":"","variableId":"10127"},{"value":"223797","title":"Ethnic Group, 2011 (QS201EW)","description":"","variableId":"10128"},{"value":"222127","title":"Ethnic Group, 2011 (QS201EW)","description":"","variableId":"10129"},{"value":"124250","title":"Ethnic Group, 2011 (QS201EW)","description":"","variableId":"10130"},{"value":"398515","title":"Ethnic Group, 2011 (QS201EW)","description":"","variableId":"10131"},{"value":"573931","title":"Ethnic Group, 2011 (QS201EW)","description":"","variableId":"10132"},{"value":"344597","title":"Ethnic Group, 2011 (QS201EW)","description":"","variableId":"10133"},{"value":"170112","title":"Ethnic Group, 2011 (QS201EW)","description":"","variableId":"10134"},{"value":"106020","title":"Ethnic Group, 2011 (QS201EW)","description":"","variableId":"10135"},{"value":"175021","title":"Ethnic Group, 2011 (QS201EW)","description":"","variableId":"10136"},{"value":"2064263","title":"Families with Dependent Children, 2011 (QS118EW)","description":"","variableId":"10546"},{"value":"1054104","title":"Families with Dependent Children, 2011 (QS118EW)","description":"","variableId":"10547"},{"value":"194371","title":"Families with Dependent Children, 2011 (QS118EW)","description":"","variableId":"10548"},{"value":"108096","title":"Families with Dependent Children, 2011 (QS118EW)","description":"","variableId":"10549"},{"value":"168836","title":"Families with Dependent Children, 2011 (QS118EW)","description":"","variableId":"10550"},{"value":"157813","title":"Families with Dependent Children, 2011 (QS118EW)","description":"","variableId":"10551"},{"value":"128918","title":"Families with Dependent Children, 2011 (QS118EW)","description":"","variableId":"10552"},{"value":"66732","title":"Families with Dependent Children, 2011 (QS118EW)","description":"","variableId":"10553"},{"value":"104112","title":"Families with Dependent Children, 2011 (QS118EW)","description":"","variableId":"10554"},{"value":"70235","title":"Families with Dependent Children, 2011 (QS118EW)","description":"","variableId":"10555"},{"value":"11046","title":"Families with Dependent Children, 2011 (QS118EW)","description":"","variableId":"10556"},{"value":"1845770","title":"Families with Dependent Children, 2011 (QS118EW)","description":"","variableId":"10557"},{"value":"8173941","title":"General Health, 2011 (QS302EW)","description":"","variableId":"9385"},{"value":"4127788","title":"General Health, 2011 (QS302EW)","description":"","variableId":"9386"},{"value":"2725645","title":"General Health, 2011 (QS302EW)","description":"","variableId":"9387"},{"value":"915035","title":"General Health, 2011 (QS302EW)","description":"","variableId":"9388"},{"value":"305343","title":"General Health, 2011 (QS302EW)","description":"","variableId":"9389"},{"value":"100130","title":"General Health, 2011 (QS302EW)","description":"","variableId":"9390"},{"value":"6549173","title":"Highest Level of Qualification, 2011 (QS501EW)","description":"","variableId":"10137"},{"value":"1152517","title":"Highest Level of Qualification, 2011 (QS501EW)","description":"","variableId":"10138"},{"value":"107665","title":"Highest Level of Qualification, 2011 (QS501EW)","description":"","variableId":"10139"},{"value":"702687","title":"Highest Level of Qualification, 2011 (QS501EW)","description":"","variableId":"10140"},{"value":"775928","title":"Highest Level of Qualification, 2011 (QS501EW)","description":"","variableId":"10141"},{"value":"685508","title":"Highest Level of Qualification, 2011 (QS501EW)","description":"","variableId":"10142"},{"value":"2470225","title":"Highest Level of Qualification, 2011 (QS501EW)","description":"","variableId":"10143"},{"value":"654643","title":"Highest Level of Qualification, 2011 (QS501EW)","description":"","variableId":"10144"},{"value":"346106","title":"Hours Worked, 2011 (QS604EW)","description":"","variableId":"9747"},{"value":"678947","title":"Hours Worked, 2011 (QS604EW)","description":"","variableId":"9748"},{"value":"2338716","title":"Hours Worked, 2011 (QS604EW)","description":"","variableId":"9749"},{"value":"635128","title":"Hours Worked, 2011 (QS604EW)","description":"","variableId":"9750"},{"value":"1025053","title":"Hours Worked, 2011 (QS604EW)","description":"","variableId":"9751"},{"value":"2973844","title":"Hours Worked, 2011 (QS604EW)","description":"","variableId":"9752"},{"value":"3998897","title":"Hours Worked, 2011 (QS604EW)","description":"","variableId":"9753"},{"value":"8073700","title":"Household Composition (Alternative Child and Adult Definitions) - People, 2011 (QS114EW)","description":"","variableId":"9391"},{"value":"1030558","title":"Household Composition (Alternative Child and Adult Definitions) - People, 2011 (QS114EW)","description":"","variableId":"9392"},{"value":"312022","title":"Household Composition (Alternative Child and Adult Definitions) - People, 2011 (QS114EW)","description":"","variableId":"9393"},{"value":"718536","title":"Household Composition (Alternative Child and Adult Definitions) - People, 2011 (QS114EW)","description":"","variableId":"9394"},{"value":"7043142","title":"Household Composition (Alternative Child and Adult Definitions) - People, 2011 (QS114EW)","description":"","variableId":"9395"},{"value":"531998","title":"Household Composition (Alternative Child and Adult Definitions) - People, 2011 (QS114EW)","description":"","variableId":"9396"},{"value":"485612","title":"Household Composition (Alternative Child and Adult Definitions) - People, 2011 (QS114EW)","description":"","variableId":"9397"},{"value":"1430617","title":"Household Composition (Alternative Child and Adult Definitions) - People, 2011 (QS114EW)","description":"","variableId":"9398"},{"value":"1188290","title":"Household Composition (Alternative Child and Adult Definitions) - People, 2011 (QS114EW)","description":"","variableId":"9399"},{"value":"503531","title":"Household Composition (Alternative Child and Adult Definitions) - People, 2011 (QS114EW)","description":"","variableId":"9400"},{"value":"1149655","title":"Household Composition (Alternative Child and Adult Definitions) - People, 2011 (QS114EW)","description":"","variableId":"9401"},{"value":"1753439","title":"Household Composition (Alternative Child and Adult Definitions) - People, 2011 (QS114EW)","description":"","variableId":"9402"},{"value":"3266173","title":"Household Composition - (Alternative Child and Adult Definitions) - Households, 2011 (QS115EW)","description":"","variableId":"10884"},{"value":"1030558","title":"Household Composition - (Alternative Child and Adult Definitions) - Households, 2011 (QS115EW)","description":"","variableId":"10885"},{"value":"312022","title":"Household Composition - (Alternative Child and Adult Definitions) - Households, 2011 (QS115EW)","description":"","variableId":"10886"},{"value":"718536","title":"Household Composition - (Alternative Child and Adult Definitions) - Households, 2011 (QS115EW)","description":"","variableId":"10887"},{"value":"2235615","title":"Household Composition - (Alternative Child and Adult Definitions) - Households, 2011 (QS115EW)","description":"","variableId":"10888"},{"value":"198159","title":"Household Composition - (Alternative Child and Adult Definitions) - Households, 2011 (QS115EW)","description":"","variableId":"10889"},{"value":"242806","title":"Household Composition - (Alternative Child and Adult Definitions) - Households, 2011 (QS115EW)","description":"","variableId":"10890"},{"value":"408996","title":"Household Composition - (Alternative Child and Adult Definitions) - Households, 2011 (QS115EW)","description":"","variableId":"10891"},{"value":"594145","title":"Household Composition - (Alternative Child and Adult Definitions) - Households, 2011 (QS115EW)","description":"","variableId":"10892"},{"value":"93926","title":"Household Composition - (Alternative Child and Adult Definitions) - Households, 2011 (QS115EW)","description":"","variableId":"10893"},{"value":"218734","title":"Household Composition - (Alternative Child and Adult Definitions) - Households, 2011 (QS115EW)","description":"","variableId":"10894"},{"value":"478849","title":"Household Composition - (Alternative Child and Adult Definitions) - Households, 2011 (QS115EW)","description":"","variableId":"10895"},{"value":"3266173","title":"Household Composition - Households, 2011 (QS113EW)","description":"","variableId":"8925"},{"value":"1030558","title":"Household Composition - Households, 2011 (QS113EW)","description":"","variableId":"8926"},{"value":"312022","title":"Household Composition - Households, 2011 (QS113EW)","description":"","variableId":"8927"},{"value":"718536","title":"Household Composition - Households, 2011 (QS113EW)","description":"","variableId":"8928"},{"value":"1746841","title":"Household Composition - Households, 2011 (QS113EW)","description":"","variableId":"8929"},{"value":"134063","title":"Household Composition - Households, 2011 (QS113EW)","description":"","variableId":"8930"},{"value":"907911","title":"Household Composition - Households, 2011 (QS113EW)","description":"","variableId":"8931"},{"value":"262771","title":"Household Composition - Households, 2011 (QS113EW)","description":"","variableId":"8932"},{"value":"186219","title":"Household Composition - Households, 2011 (QS113EW)","description":"","variableId":"8933"},{"value":"303367","title":"Household Composition - Households, 2011 (QS113EW)","description":"","variableId":"8934"},{"value":"155554","title":"Household Composition - Households, 2011 (QS113EW)","description":"","variableId":"8935"},{"value":"8496","title":"Household Composition - Households, 2011 (QS113EW)","description":"","variableId":"8936"},{"value":"7938","title":"Household Composition - Households, 2011 (QS113EW)","description":"","variableId":"8937"},{"value":"272","title":"Household Composition - Households, 2011 (QS113EW)","description":"","variableId":"8938"},{"value":"182","title":"Household Composition - Households, 2011 (QS113EW)","description":"","variableId":"8939"},{"value":"104","title":"Household Composition - Households, 2011 (QS113EW)","description":"","variableId":"8940"},{"value":"282907","title":"Household Composition - Households, 2011 (QS113EW)","description":"","variableId":"8941"},{"value":"178845","title":"Household Composition - Households, 2011 (QS113EW)","description":"","variableId":"8942"},{"value":"46341","title":"Household Composition - Households, 2011 (QS113EW)","description":"","variableId":"8943"},{"value":"45433","title":"Household Composition - Households, 2011 (QS113EW)","description":"","variableId":"8944"},{"value":"12288","title":"Household Composition - Households, 2011 (QS113EW)","description":"","variableId":"8945"},{"value":"413464","title":"Household Composition - Households, 2011 (QS113EW)","description":"","variableId":"8946"},{"value":"153648","title":"Household Composition - Households, 2011 (QS113EW)","description":"","variableId":"8947"},{"value":"125338","title":"Household Composition - Households, 2011 (QS113EW)","description":"","variableId":"8948"},{"value":"134478","title":"Household Composition - Households, 2011 (QS113EW)","description":"","variableId":"8949"},{"value":"488774","title":"Household Composition - Households, 2011 (QS113EW)","description":"","variableId":"8950"},{"value":"70468","title":"Household Composition - Households, 2011 (QS113EW)","description":"","variableId":"8951"},{"value":"78575","title":"Household Composition - Households, 2011 (QS113EW)","description":"","variableId":"8952"},{"value":"24384","title":"Household Composition - Households, 2011 (QS113EW)","description":"","variableId":"8953"},{"value":"8660","title":"Household Composition - Households, 2011 (QS113EW)","description":"","variableId":"8954"},{"value":"306687","title":"Household Composition - Households, 2011 (QS113EW)","description":"","variableId":"8955"},{"value":"8073700","title":"Household Composition - People, 2011 (QS112EW)","description":"","variableId":"8956"},{"value":"1030558","title":"Household Composition - People, 2011 (QS112EW)","description":"","variableId":"8957"},{"value":"312022","title":"Household Composition - People, 2011 (QS112EW)","description":"","variableId":"8958"},{"value":"718536","title":"Household Composition - People, 2011 (QS112EW)","description":"","variableId":"8959"},{"value":"5227195","title":"Household Composition - People, 2011 (QS112EW)","description":"","variableId":"8960"},{"value":"268226","title":"Household Composition - People, 2011 (QS112EW)","description":"","variableId":"8961"},{"value":"3076096","title":"Household Composition - People, 2011 (QS112EW)","description":"","variableId":"8962"},{"value":"525542","title":"Household Composition - People, 2011 (QS112EW)","description":"","variableId":"8963"},{"value":"619057","title":"Household Composition - People, 2011 (QS112EW)","description":"","variableId":"8964"},{"value":"1393123","title":"Household Composition - People, 2011 (QS112EW)","description":"","variableId":"8965"},{"value":"538374","title":"Household Composition - People, 2011 (QS112EW)","description":"","variableId":"8966"},{"value":"17788","title":"Household Composition - People, 2011 (QS112EW)","description":"","variableId":"8967"},{"value":"15876","title":"Household Composition - People, 2011 (QS112EW)","description":"","variableId":"8968"},{"value":"826","title":"Household Composition - People, 2011 (QS112EW)","description":"","variableId":"8969"},{"value":"765","title":"Household Composition - People, 2011 (QS112EW)","description":"","variableId":"8970"},{"value":"321","title":"Household Composition - People, 2011 (QS112EW)","description":"","variableId":"8971"},{"value":"746694","title":"Household Composition - People, 2011 (QS112EW)","description":"","variableId":"8972"},{"value":"357690","title":"Household Composition - People, 2011 (QS112EW)","description":"","variableId":"8973"},{"value":"145188","title":"Household Composition - People, 2011 (QS112EW)","description":"","variableId":"8974"},{"value":"202865","title":"Household Composition - People, 2011 (QS112EW)","description":"","variableId":"8975"},{"value":"40951","title":"Household Composition - People, 2011 (QS112EW)","description":"","variableId":"8976"},{"value":"1118391","title":"Household Composition - People, 2011 (QS112EW)","description":"","variableId":"8977"},{"value":"342190","title":"Household Composition - People, 2011 (QS112EW)","description":"","variableId":"8978"},{"value":"468443","title":"Household Composition - People, 2011 (QS112EW)","description":"","variableId":"8979"},{"value":"307758","title":"Household Composition - People, 2011 (QS112EW)","description":"","variableId":"8980"},{"value":"1815947","title":"Household Composition - People, 2011 (QS112EW)","description":"","variableId":"8981"},{"value":"303341","title":"Household Composition - People, 2011 (QS112EW)","description":"","variableId":"8982"},{"value":"452892","title":"Household Composition - People, 2011 (QS112EW)","description":"","variableId":"8983"},{"value":"78050","title":"Household Composition - People, 2011 (QS112EW)","description":"","variableId":"8984"},{"value":"19954","title":"Household Composition - People, 2011 (QS112EW)","description":"","variableId":"8985"},{"value":"961710","title":"Household Composition - People, 2011 (QS112EW)","description":"","variableId":"8986"},{"value":"3266173","title":"Household Lifestage, 2011 (QS111EW)","description":"","variableId":"9660"},{"value":"798750","title":"Household Lifestage, 2011 (QS111EW)","description":"","variableId":"9661"},{"value":"202761","title":"Household Lifestage, 2011 (QS111EW)","description":"","variableId":"9662"},{"value":"347905","title":"Household Lifestage, 2011 (QS111EW)","description":"","variableId":"9663"},{"value":"248084","title":"Household Lifestage, 2011 (QS111EW)","description":"","variableId":"9664"},{"value":"1402459","title":"Household Lifestage, 2011 (QS111EW)","description":"","variableId":"9665"},{"value":"359426","title":"Household Lifestage, 2011 (QS111EW)","description":"","variableId":"9666"},{"value":"350192","title":"Household Lifestage, 2011 (QS111EW)","description":"","variableId":"9667"},{"value":"692841","title":"Household Lifestage, 2011 (QS111EW)","description":"","variableId":"9668"},{"value":"457898","title":"Household Lifestage, 2011 (QS111EW)","description":"","variableId":"9669"},{"value":"156349","title":"Household Lifestage, 2011 (QS111EW)","description":"","variableId":"9670"},{"value":"245167","title":"Household Lifestage, 2011 (QS111EW)","description":"","variableId":"9671"},{"value":"56382","title":"Household Lifestage, 2011 (QS111EW)","description":"","variableId":"9672"},{"value":"607066","title":"Household Lifestage, 2011 (QS111EW)","description":"","variableId":"9673"},{"value":"312022","title":"Household Lifestage, 2011 (QS111EW)","description":"","variableId":"9674"},{"value":"282508","title":"Household Lifestage, 2011 (QS111EW)","description":"","variableId":"9675"},{"value":"12536","title":"Household Lifestage, 2011 (QS111EW)","description":"","variableId":"9676"},{"value":"1030558","title":"Household Size, 2011 (QS406EW)","description":"","variableId":"9875"},{"value":"947805","title":"Household Size, 2011 (QS406EW)","description":"","variableId":"9876"},{"value":"526610","title":"Household Size, 2011 (QS406EW)","description":"","variableId":"9877"},{"value":"439852","title":"Household Size, 2011 (QS406EW)","description":"","variableId":"9878"},{"value":"195395","title":"Household Size, 2011 (QS406EW)","description":"","variableId":"9879"},{"value":"85719","title":"Household Size, 2011 (QS406EW)","description":"","variableId":"9880"},{"value":"22396","title":"Household Size, 2011 (QS406EW)","description":"","variableId":"9881"},{"value":"17838","title":"Household Size, 2011 (QS406EW)","description":"","variableId":"9882"},{"value":"3266173","title":"Household Size, 2011 (QS406EW)","description":"","variableId":"9883"},{"value":"3387255","title":"Household Spaces, 2011 (QS417EW)","description":"","variableId":"10145"},{"value":"3266173","title":"Household Spaces, 2011 (QS417EW)","description":"","variableId":"10146"},{"value":"121082","title":"Household Spaces, 2011 (QS417EW)","description":"","variableId":"10147"},{"value":"3266173","title":"Household Type, 2011 (QS116EW)","description":"","variableId":"9342"},{"value":"1030558","title":"Household Type, 2011 (QS116EW)","description":"","variableId":"9343"},{"value":"560627","title":"Household Type, 2011 (QS116EW)","description":"","variableId":"9344"},{"value":"609346","title":"Household Type, 2011 (QS116EW)","description":"","variableId":"9345"},{"value":"507","title":"Household Type, 2011 (QS116EW)","description":"","variableId":"9346"},{"value":"9615","title":"Household Type, 2011 (QS116EW)","description":"","variableId":"9347"},{"value":"101065","title":"Household Type, 2011 (QS116EW)","description":"","variableId":"9348"},{"value":"234944","title":"Household Type, 2011 (QS116EW)","description":"","variableId":"9349"},{"value":"325806","title":"Household Type, 2011 (QS116EW)","description":"","variableId":"9350"},{"value":"153753","title":"Household Type, 2011 (QS116EW)","description":"","variableId":"9351"},{"value":"23607","title":"Household Type, 2011 (QS116EW)","description":"","variableId":"9352"},{"value":"216345","title":"Household Type, 2011 (QS116EW)","description":"","variableId":"9353"}]