[{"subjectId":"58","name":"Census"},{"subjectId":"3","name":"Crime and Safety"},{"subjectId":"4","name":"Economic Deprivation"},{"subjectId":"5","name":"Education, Skills and Training"},{"subjectId":"6","name":"Health and Care"},{"subjectId":"7","name":"Housing"},{"subjectId":"46","name":"Indicators"},{"subjectId":"10","name":"Indices of Deprivation and Classification"},{"subjectId":"14","name":"People and Society: Income and Lifestyles"},{"subjectId":"13","name":"People and Society: Population and Migration"},{"subjectId":"8","name":"Physical Environment"},{"subjectId":"9","name":"Work Deprivation"}]